README.rst
setup.py
36_chambers.egg-info/PKG-INFO
36_chambers.egg-info/SOURCES.txt
36_chambers.egg-info/dependency_links.txt
36_chambers.egg-info/top_level.txt
chambers/__init__.py
chambers/chamber.py