Metadata-Version: 1.1
Name: 36-chambers
Version: 0.0.1
Summary: Python Library for Binary Ninja
Home-page: https://www.github.com/mgoffin/36-chambers
Author: Mike Goffin
Author-email: mgoffin@gmail.com
License: MIT
Keywords: binary ninja 36 chambers
Platform: UNKNOWN
Classifier: Development Status :: 3 - Alpha
Classifier: Intended Audience :: Developers
Classifier: Topic :: Software Development :: Build Tools
Classifier: License :: OSI Approved :: MIT License
Classifier: Programming Language :: Python :: 2.7
